bib_updater.py
dblp_client.py
main.py
bibboost-0.1.1.dist-info/METADATA
bibboost-0.1.1.dist-info/WHEEL
bibboost-0.1.1.dist-info/entry_points.txt
bibboost-0.1.1.dist-info/top_level.txt
bibboost-0.1.1.dist-info/RECORD
