Metadata-Version: 2.4
Name: bibboost
Version: 0.1.1
Summary: Boost your bibliography by updating BibTeX entries with published conference versions
Requires-Python: >=3.11
Requires-Dist: bibtexparser>=1.4.3
Requires-Dist: click>=8.3.0
Requires-Dist: python-dotenv>=1.1.1
Requires-Dist: questionary>=2.1.1
Requires-Dist: requests>=2.32.5
Requires-Dist: tenacity>=9.1.2
